cjm_kaggle_utils/__init__.py
cjm_kaggle_utils/_modidx.py
cjm_kaggle_utils/core.py
cjm_kaggle_utils-0.0.5.dist-info/LICENSE
cjm_kaggle_utils-0.0.5.dist-info/METADATA
cjm_kaggle_utils-0.0.5.dist-info/WHEEL
cjm_kaggle_utils-0.0.5.dist-info/entry_points.txt
cjm_kaggle_utils-0.0.5.dist-info/top_level.txt
cjm_kaggle_utils-0.0.5.dist-info/RECORD
